odoo/addons/bi_view_editor_spreadsheet_dashboard/README.rst
odoo/addons/bi_view_editor_spreadsheet_dashboard/__init__.py
odoo/addons/bi_view_editor_spreadsheet_dashboard/__manifest__.py
odoo/addons/bi_view_editor_spreadsheet_dashboard/i18n/bi_view_editor_spreadsheet_dashboard.pot
odoo/addons/bi_view_editor_spreadsheet_dashboard/i18n/it.po
odoo/addons/bi_view_editor_spreadsheet_dashboard/readme/CONTRIBUTORS.md
odoo/addons/bi_view_editor_spreadsheet_dashboard/readme/DESCRIPTION.md
odoo/addons/bi_view_editor_spreadsheet_dashboard/static/description/icon.png
odoo/addons/bi_view_editor_spreadsheet_dashboard/static/description/index.html
odoo/addons/bi_view_editor_spreadsheet_dashboard/views/menus.xml
odoo_addon_bi_view_editor_spreadsheet_dashboard-17.0.1.0.0.2.dist-info/METADATA
odoo_addon_bi_view_editor_spreadsheet_dashboard-17.0.1.0.0.2.dist-info/WHEEL
odoo_addon_bi_view_editor_spreadsheet_dashboard-17.0.1.0.0.2.dist-info/top_level.txt
odoo_addon_bi_view_editor_spreadsheet_dashboard-17.0.1.0.0.2.dist-info/RECORD
