Metadata-Version: 2.1
Name: odoo-addon-bi_view_editor_spreadsheet_dashboard
Version: 17.0.1.0.0.2
Requires-Python: >=3.10
Requires-Dist: odoo-addon-bi_view_editor>=17.0dev,<17.1dev
Requires-Dist: odoo>=17.0a,<17.1dev
Summary: Glue module for BI View Editor and Spreadsheet Dashboard
Home-page: https://github.com/OCA/reporting-engine
License: AGPL-3
Author: Coop IT Easy SC, Odoo Community Association (OCA)
Author-email: support@odoo-community.org
Classifier: Programming Language :: Python
Classifier: Framework :: Odoo
Classifier: Framework :: Odoo :: 17.0
Classifier: License :: OSI Approved :: GNU Affero General Public License v3
